ace_network_manager/__init__.py
ace_network_manager/__main__.py
ace_network_manager/cli.py
ace_network_manager/backup/__init__.py
ace_network_manager/backup/manager.py
ace_network_manager/core/__init__.py
ace_network_manager/core/constants.py
ace_network_manager/core/exceptions.py
ace_network_manager/core/manager.py
ace_network_manager/daemon/__init__.py
ace_network_manager/daemon/monitor.py
ace_network_manager/network/__init__.py
ace_network_manager/network/backend.py
ace_network_manager/network/connectivity.py
ace_network_manager/network/models.py
ace_network_manager/network/validator.py
ace_network_manager/state/__init__.py
ace_network_manager/state/models.py
ace_network_manager/state/tracker.py
ace_network_manager/systemd/__init__.py
ace_network_manager/systemd/integration.py
ace_network_manager/systemd/units.py
ace_network_manager/utils/__init__.py
ace_network_manager/utils/filesystem.py
ace_network_manager/utils/locking.py
ace_network_manager/watcher/__init__.py
ace_network_manager/watcher/confirmation.py
ace_network_manager/watcher/timeout.py
ace_network_manager-0.3.3.dist-info/METADATA
ace_network_manager-0.3.3.dist-info/WHEEL
ace_network_manager-0.3.3.dist-info/entry_points.txt
ace_network_manager-0.3.3.dist-info/licenses/LICENSE
ace_network_manager-0.3.3.dist-info/RECORD
