Metadata-Version: 2.4
Name: ace-network-manager
Version: 0.3.3
Summary: Safe network configuration manager for edge deployments with automatic rollback
Project-URL: Homepage, https://github.com/ACE-IoT-Solutions/ace-network-manager
Project-URL: Repository, https://github.com/ACE-IoT-Solutions/ace-network-manager
Project-URL: Issues, https://github.com/ACE-IoT-Solutions/ace-network-manager/issues
Author-email: Andrew Rodgers <andrew@aceiotsolutions.com>
License: MIT
License-File: LICENSE
Keywords: configuration,edge,iot,netplan,network,rollback
Classifier: Development Status :: 3 - Alpha
Classifier: Intended Audience :: System Administrators
Classifier: License :: OSI Approved :: MIT License
Classifier: Operating System :: POSIX :: Linux
Classifier: Programming Language :: Python :: 3
Classifier: Programming Language :: Python :: 3.10
Classifier: Programming Language :: Python :: 3.11
Classifier: Programming Language :: Python :: 3.12
Classifier: Programming Language :: Python :: 3.13
Classifier: Topic :: System :: Networking
Classifier: Topic :: System :: Systems Administration
Requires-Python: >=3.10
Requires-Dist: click>=8.3.0
Requires-Dist: pydantic-settings>=2.7.1
Requires-Dist: pydantic>=2.10.6
Requires-Dist: pyyaml>=6.0.2
